{
  "id": "60925ed7491576001ce5549f",
  "title": "ほぼ毎日映画観る2021春 dnin",
  "created": 1620205273,
  "updated": 1620290288,
  "lines": [
    {
      "id": "60925ed7491576001ce5549f",
      "text": "ほぼ毎日映画観る2021春 dnin",
      "userId": "6055950b87138f0022246f59",
      "created": 1620205273,
      "updated": 1620257482
    },
    {
      "id": "60925edf246f590000fb2c32",
      "text": "[********** [ボス・ベイビー.icon][下妻物語.icon][リミットレス.icon][ベイブ.icon][ソーセージ・パーティー.icon][星の王子ニューヨークへ行く.icon][星の王子ニューヨークへ行く 2.icon][サイケデリック航空.icon][あなたのお電話はわたしたちにとって重要です。.icon][365日のシンプルライフ.icon][レディ・プレイヤー1.icon][シャイニング.icon][ドクター・ドリトル.icon][コーヒーが冷めないうちに.icon][ヒート(映画).icon][エイプリルフールズ.icon][ジャッジ！.icon][ローサは密告された.icon][インスタキラー.icon][虹色ほたる ～永遠の夏休み～.icon][銀座の女.icon][色の街.icon][雨(映画).icon][小公子.icon][地獄への道.icon][チップス先生さようなら.icon][大きな春子ちゃん.icon][一度死んでみた.icon][ゾラの生涯.icon][民衆の敵(1931年の映画).icon][月世界旅行.icon][行け! あひるお姉さん.icon][Two Balloons.icon][百万円と苦虫女.icon][俺はまだ本気出してないだけ.icon][日本沈没.icon][クリスマス・キャロル.icon]]",
      "userId": "6055950b87138f0022246f59",
      "created": 1620205279,
      "updated": 1620287562
    },
    {
      "id": "60932f03246f590000fac8b7",
      "text": "",
      "userId": "6055950b87138f0022246f59",
      "created": 1620258566,
      "updated": 1620258566
    },
    {
      "id": "609389cbb3e7ed0000a520b8",
      "text": "文化的になれそう",
      "userId": "5e644eb64b223c0017b3e7ed",
      "created": 1620281804,
      "updated": 1620281822
    },
    {
      "id": "609389ddb3e7ed0000a520ba",
      "text": "[レディ・プレイヤー1]しかみたことないなぁ",
      "userId": "5e644eb64b223c0017b3e7ed",
      "created": 1620281822,
      "updated": 1620281843
    },
    {
      "id": "609389ccb3e7ed0000a520b9",
      "text": "",
      "userId": "5e644eb64b223c0017b3e7ed",
      "created": 1620281805,
      "updated": 1620281805
    },
    {
      "id": "6093aad5246f590000786420",
      "text": "最近流行りのビジネス書を読むより、アマプラで映画見たほうが啓発された感がするぜ[dnin.icon]",
      "userId": "6055950b87138f0022246f59",
      "created": 1620290261,
      "updated": 1620290288
    },
    {
      "id": "6093aad8246f590000786421",
      "text": "",
      "userId": "6055950b87138f0022246f59",
      "created": 1620290264,
      "updated": 1620290264
    }
  ]
}