{
  "id": "60bc6785cdfa9a001c6c86d2",
  "title": "まちの駅",
  "created": 1622960007,
  "updated": 1622960007,
  "lines": [
    {
      "id": "60bc6785cdfa9a001c6c86d2",
      "text": "まちの駅",
      "userId": "566fa156776c9b11008ee92a",
      "created": 1622960007,
      "updated": 1622960007
    },
    {
      "id": "60bc67868ee92a00005fd384",
      "text": "[http://www.machinoeki.com/]",
      "userId": "566fa156776c9b11008ee92a",
      "created": 1622960007,
      "updated": 1622960007
    },
    {
      "id": "60bc67868ee92a00005fd385",
      "text": "[https://gyazo.com/9d36d89b80b642d6c0eeac7d81f7475f]",
      "userId": "566fa156776c9b11008ee92a",
      "created": 1622960007,
      "updated": 1622960007
    },
    {
      "id": "60bc67868ee92a00005fd386",
      "text": "",
      "userId": "566fa156776c9b11008ee92a",
      "created": 1622960007,
      "updated": 1622960007
    }
  ]
}