{
  "id": "60a8c4431f91e000234a5112",
  "title": "エンジニア認証",
  "created": 1621673029,
  "updated": 1635476126,
  "lines": [
    {
      "id": "60a8c4431f91e000234a5112",
      "text": "エンジニア認証",
      "userId": "566fa156776c9b11008ee92a",
      "created": 1621673029,
      "updated": 1621673029
    },
    {
      "id": "60a8c4458ee92a000025d0af",
      "text": " `65525`とか聞くと気持ち悪さを感じる",
      "userId": "566fa156776c9b11008ee92a",
      "created": 1621673029,
      "updated": 1621673067
    },
    {
      "id": "60a8c4998ee92a000025d0b4",
      "text": " `404`と聞くと残念さを感じる",
      "userId": "566fa156776c9b11008ee92a",
      "created": 1621673113,
      "updated": 1621673123
    },
    {
      "id": "617b62894bb2e2000077e75a",
      "text": " `256`等の数をキリがいいと感じる",
      "userId": "5e8944948a182900174bb2e2",
      "created": 1635476106,
      "updated": 1635476126
    },
    {
      "id": "60a8c4498ee92a000025d0b3",
      "text": " [https://4.bp.blogspot.com/-02mTT_mAcF0/V4SA7PnHXwI/AAAAAAAA8OE/bMCTmcMMax8gZjBqtKsP-mBuX_8955-QACLcB/s400/computer_hub_loop_setsuzoku.png]",
      "userId": "612309a719e67d001dd0ca1c",
      "created": 1621673033,
      "updated": 1635422948
    },
    {
      "id": "617a92cad0ca1c0000bda50f",
      "text": "",
      "userId": "612309a719e67d001dd0ca1c",
      "created": 1635422948,
      "updated": 1635422948
    },
    {
      "id": "60a8c5a9246f5900004e9841",
      "text": "  これを見ると身の毛がよだつ",
      "userId": "6055950b87138f0022246f59",
      "created": 1621673411,
      "updated": 1621673416
    },
    {
      "id": "60a8d2c45b98c200006cb721",
      "text": " パイプ椅子３つで仮眠をとることができる",
      "userId": "6055950b87138f0022246f59",
      "created": 1621676740,
      "updated": 1621680729
    },
    {
      "id": "60a8f40d79d3a900000b3edb",
      "text": " `rm -rf /`は見るだけで怖い",
      "userId": "5a4873ab2e26fb001479d3a9",
      "created": 1621685262,
      "updated": 1621685287
    },
    {
      "id": "60a9b1238ee92a0000ecb900",
      "text": " 左括弧と右括弧の数が違うと発狂する",
      "userId": "566fa156776c9b11008ee92a",
      "created": 1621733667,
      "updated": 1621733683
    },
    {
      "id": "617b183779d3a90000311f6e",
      "text": " 全角スペースがあると発狂する",
      "userId": "5a4873ab2e26fb001479d3a9",
      "created": 1635457081,
      "updated": 1635457087
    },
    {
      "id": "617b184579d3a90000311f6f",
      "text": " 全角英数字があると発狂する",
      "userId": "5a4873ab2e26fb001479d3a9",
      "created": 1635457094,
      "updated": 1635457098
    },
    {
      "id": "60a9b1238ee92a0000ecb901",
      "text": "",
      "userId": "566fa156776c9b11008ee92a",
      "created": 1621733668,
      "updated": 1621733668
    },
    {
      "id": "60a8c4458ee92a000025d0b0",
      "text": "#認証",
      "userId": "566fa156776c9b11008ee92a",
      "created": 1621673029,
      "updated": 1621673031
    },
    {
      "id": "60a8c4458ee92a000025d0b1",
      "text": "",
      "userId": "566fa156776c9b11008ee92a",
      "created": 1621673029,
      "updated": 1621673029
    },
    {
      "id": "617a9288d0ca1c0000bda50c",
      "text": "　何の漫画だったっけ？",
      "userId": "612309a719e67d001dd0ca1c",
      "created": 1635422883,
      "updated": 1635422893
    },
    {
      "id": "617a9292d0ca1c0000bda50e",
      "text": "　\tいくつか質問して、「こいつだ、連れてけ！」ってやつ",
      "userId": "612309a719e67d001dd0ca1c",
      "created": 1635422893,
      "updated": 1635422909
    },
    {
      "id": "617a9289d0ca1c0000bda50d",
      "text": "",
      "userId": "612309a719e67d001dd0ca1c",
      "created": 1635422883,
      "updated": 1635422883
    }
  ]
}