{
  "id": "607838e1882d8d001c1f5458",
  "title": "クオカード",
  "created": 1618491621,
  "updated": 1618491634,
  "lines": [
    {
      "id": "607838e1882d8d001c1f5458",
      "text": "クオカード",
      "userId": "6055950b87138f0022246f59",
      "created": 1618491621,
      "updated": 1618491621
    },
    {
      "id": "607838e5246f590000cb1dea",
      "text": "[クオカードPay]",
      "userId": "6055950b87138f0022246f59",
      "created": 1618491622,
      "updated": 1618491634
    },
    {
      "id": "607838f1246f590000cb1dec",
      "text": "",
      "userId": "6055950b87138f0022246f59",
      "created": 1618491634,
      "updated": 1618491634
    },
    {
      "id": "607838e5246f590000cb1deb",
      "text": "",
      "userId": "6055950b87138f0022246f59",
      "created": 1618491622,
      "updated": 1618491622
    }
  ]
}