{
  "id": "607981c1dcdcd70022137cbc",
  "title": "バースデーワンダーランド",
  "created": 1618575815,
  "updated": 1618576080,
  "lines": [
    {
      "id": "607981c1dcdcd70022137cbc",
      "text": "バースデーワンダーランド",
      "userId": "6055950b87138f0022246f59",
      "created": 1618575815,
      "updated": 1618575815
    },
    {
      "id": "60798230246f5900000cf76b",
      "text": "https://www.amazon.co.jp/バースデー・ワンダーランド-原恵一/dp/B0821XZHX6",
      "userId": "6055950b87138f0022246f59",
      "created": 1618575921,
      "updated": 1618575921
    },
    {
      "id": "607981c7246f5900000cf766",
      "text": "[https://gyazo.com/227fff9f8aeb1a0d36af99b8cce3940d]",
      "userId": "6055950b87138f0022246f59",
      "created": 1618575815,
      "updated": 1618575855
    },
    {
      "id": "607981ef246f5900000cf769",
      "text": "　猫様に人間が処罰されるシーンが性癖に刺さった[dnin.icon]",
      "userId": "6055950b87138f0022246f59",
      "created": 1618575855,
      "updated": 1618575878
    },
    {
      "id": "607982c1246f5900000cf770",
      "text": "　ストーリーを期待しないほうが良い。動く絵本だと思ってみたほうが。",
      "userId": "6055950b87138f0022246f59",
      "created": 1618576066,
      "updated": 1618576080
    },
    {
      "id": "607981f4246f5900000cf76a",
      "text": "",
      "userId": "6055950b87138f0022246f59",
      "created": 1618575860,
      "updated": 1618575860
    },
    {
      "id": "60798286246f5900000cf76c",
      "text": "[https://www.youtube.com/watch?v=J8XCIoW_8-M]",
      "userId": "6055950b87138f0022246f59",
      "created": 1618576007,
      "updated": 1618576007
    },
    {
      "id": "60798286246f5900000cf76e",
      "text": " このCMを見て観た",
      "userId": "6055950b87138f0022246f59",
      "created": 1618576007,
      "updated": 1618576021
    },
    {
      "id": "60798286246f5900000cf76d",
      "text": "",
      "userId": "6055950b87138f0022246f59",
      "created": 1618576007,
      "updated": 1618576007
    }
  ]
}