{
  "id": "6082c5d99c18bd001c55a1f9",
  "title": "ポポラマーマ",
  "created": 1619183069,
  "updated": 1619183127,
  "lines": [
    {
      "id": "6082c5d99c18bd001c55a1f9",
      "text": "ポポラマーマ",
      "userId": "6055950b87138f0022246f59",
      "created": 1619183069,
      "updated": 1619183069
    },
    {
      "id": "6082c5dd246f5900004d8a84",
      "text": "生[パスタ]の[チェーン店]",
      "userId": "6055950b87138f0022246f59",
      "created": 1619183069,
      "updated": 1619183103
    },
    {
      "id": "6082c5df246f5900004d8a85",
      "text": "https://www.popolamama.com/",
      "userId": "6055950b87138f0022246f59",
      "created": 1619183072,
      "updated": 1619183080
    },
    {
      "id": "6082c5e8246f5900004d8a86",
      "text": "[https://gyazo.com/0bcc566dc70f8471618ed0bd32b54d00]",
      "userId": "6055950b87138f0022246f59",
      "created": 1619183080,
      "updated": 1619183127
    },
    {
      "id": "6082c617246f5900004d8a89",
      "text": "",
      "userId": "6055950b87138f0022246f59",
      "created": 1619183127,
      "updated": 1619183127
    },
    {
      "id": "6082c5f1246f5900004d8a87",
      "text": "ケーキもうまい[dnin.icon]",
      "userId": "6055950b87138f0022246f59",
      "created": 1619183089,
      "updated": 1619183107
    },
    {
      "id": "6082c5f1246f5900004d8a88",
      "text": "",
      "userId": "6055950b87138f0022246f59",
      "created": 1619183090,
      "updated": 1619183090
    }
  ]
}