{
  "id": "60307046606c97001f062103",
  "title": "マイナンバーカード",
  "created": 1613787227,
  "updated": 1613815871,
  "lines": [
    {
      "id": "60307046606c97001f062103",
      "text": "マイナンバーカード",
      "userId": "566fa156776c9b11008ee92a",
      "created": 1613787227,
      "updated": 1613787227
    },
    {
      "id": "6030979175892100000b84f0",
      "text": "　カード自体は10年ごと(未成年者は5年)に更新",
      "userId": "60226bcd2fbabe0022758921",
      "created": 1613797265,
      "updated": 1613797340
    },
    {
      "id": "6030979d75892100000b84f1",
      "text": "　カードの中にある電子証明書は5年ごとに更新",
      "userId": "60226bcd2fbabe0022758921",
      "created": 1613797278,
      "updated": 1613797333
    },
    {
      "id": "6030989075892100000b84f4",
      "text": "　 code:なぜマイナンバーカードと電子証明書で有効期限が異なっているのでしょうか。",
      "userId": "60226bcd2fbabe0022758921",
      "created": 1613797520,
      "updated": 1613797547
    },
    {
      "id": "603098a575892100000b84f6",
      "text": "　 >オンライン上での本人確認ができる電子証明書ですが、高い暗号技術によって、なりすましを防いでいます。",
      "userId": "60226bcd2fbabe0022758921",
      "created": 1613797541,
      "updated": 1613815379
    },
    {
      "id": "6030989175892100000b84f5",
      "text": "  > 一方で、この暗号技術を解読するための技術も日々進歩しています。ですから、解読されてしまうことのないように、電子証明書の有効期限は、カード自体よりも短い、発行の日から５回目の誕生日までとしています。",
      "userId": "60226bcd2fbabe0022758921",
      "created": 1613797521,
      "updated": 1613797521
    },
    {
      "id": "603098b375892100000b84f7",
      "text": "  >https://www.cao.go.jp/bangouseido/mailmagazine/backnumber/2020/20200221_01.html",
      "userId": "60226bcd2fbabe0022758921",
      "created": 1613797556,
      "updated": 1613797557
    },
    {
      "id": "6030705b8ee92a00003e110b",
      "text": "[https://gyazo.com/7fa6e44e5bb587a26b7255ab542b106b]",
      "userId": "566fa156776c9b11008ee92a",
      "created": 1613787227,
      "updated": 1613787227
    },
    {
      "id": "6030705b8ee92a00003e110c",
      "text": "[https://gyazo.com/492f9dd77a295a7a9285d10230b0e701 https://scrapbox.io/files/602f8aaf771b06001c8311c6.pdf]",
      "userId": "566fa156776c9b11008ee92a",
      "created": 1613787227,
      "updated": 1613787227
    },
    {
      "id": "6030705b8ee92a00003e1110",
      "text": "",
      "userId": "566fa156776c9b11008ee92a",
      "created": 1613787227,
      "updated": 1613787227
    },
    {
      "id": "6030705b8ee92a00003e1111",
      "text": " [https://qiita.com/yyu/items/aab20a0d1de7cf786409 マイナンバーカードで電子署名 - Qiita]",
      "userId": "566fa156776c9b11008ee92a",
      "created": 1613787227,
      "updated": 1613787227
    },
    {
      "id": "6030705b8ee92a00003e1112",
      "text": " [マイナンバーカードでSSHする https://www.osstech.co.jp/~hamano/posts/jpki-ssh/]",
      "userId": "566fa156776c9b11008ee92a",
      "created": 1613787227,
      "updated": 1613787227
    },
    {
      "id": "6030985975892100000b84f3",
      "text": " [内閣府マイナンバーメールマガジン https://www.cao.go.jp/bangouseido/mailmagazine/mailmagazine.html]",
      "userId": "60226bcd2fbabe0022758921",
      "created": 1613797466,
      "updated": 1613797473
    },
    {
      "id": "6030705b8ee92a00003e1113",
      "text": "",
      "userId": "566fa156776c9b11008ee92a",
      "created": 1613787227,
      "updated": 1613797242
    },
    {
      "id": "6030977a8ee92a00003e1116",
      "text": " 普通のユーザが活用できるならもっと流行ると思うのだけど [増井俊之.icon]",
      "userId": "566fa156776c9b11008ee92a",
      "created": 1613797242,
      "updated": 1613797262
    },
    {
      "id": "603097798ee92a00003e1115",
      "text": "  パソコンのデータ保護とか",
      "userId": "566fa156776c9b11008ee92a",
      "created": 1613797241,
      "updated": 1613797275
    },
    {
      "id": "6030979b8ee92a00003e1118",
      "text": "  パスワード生成とか",
      "userId": "566fa156776c9b11008ee92a",
      "created": 1613797276,
      "updated": 1613797279
    },
    {
      "id": "603098568ee92a00003e111c",
      "text": "  秘密的なデータが全部GitHubに置いてあって、マイナンバーを置いたときだけパソコンにダウンロードされるとか",
      "userId": "566fa156776c9b11008ee92a",
      "created": 1613797463,
      "updated": 1613797509
    },
    {
      "id": "603097918ee92a00003e1117",
      "text": "",
      "userId": "566fa156776c9b11008ee92a",
      "created": 1613797266,
      "updated": 1613797266
    },
    {
      "id": "6030b7478ee92a0000bb6441",
      "text": " マイナンバーカード持ってないとコンビニで買い物できないことにすれば超普及しそう [増井俊之.icon]",
      "userId": "566fa156776c9b11008ee92a",
      "created": 1613805384,
      "updated": 1613805406
    },
    {
      "id": "603098708ee92a00003e111d",
      "text": "  外人はパスポートを要求?",
      "userId": "566fa156776c9b11008ee92a",
      "created": 1613797489,
      "updated": 1613805431
    },
    {
      "id": "6030b76d8ee92a0000bb6442",
      "text": "  マイナンバーカードの所持により割引などの待遇が受けられれば普及率の向上に繋がるかと[U.icon]",
      "userId": "566fa156776c9b11008ee92a",
      "created": 1613805422,
      "updated": 1613814828
    },
    {
      "id": "6030dc2c8ee92a00004a9452",
      "text": "  それが[マイナポイント]?",
      "userId": "566fa156776c9b11008ee92a",
      "created": 1613814828,
      "updated": 1613815871
    },
    {
      "id": "6030bb8603b21000003b693c",
      "text": "",
      "userId": "5f16f6af405d31002403b210",
      "created": 1613806471,
      "updated": 1613806471
    }
  ]
}