{
  "id": "608910f2d07c18001c3b0a38",
  "title": "ヤオコー",
  "created": 1619595528,
  "updated": 1631846737,
  "lines": [
    {
      "id": "608910f2d07c18001c3b0a38",
      "text": "ヤオコー",
      "userId": "6055950b87138f0022246f59",
      "created": 1619595528,
      "updated": 1619595528
    },
    {
      "id": "60891108246f59000071389c",
      "text": "[https://gyazo.com/98dd623445ea7ed21fb85c900ca134f3]",
      "userId": "6055950b87138f0022246f59",
      "created": 1619595528,
      "updated": 1619595532
    },
    {
      "id": "6089110b246f59000071389f",
      "text": "",
      "userId": "6055950b87138f0022246f59",
      "created": 1619595532,
      "updated": 1619595532
    },
    {
      "id": "6144014c8ee92a00005fcaa4",
      "text": "#スーパー",
      "userId": "566fa156776c9b11008ee92a",
      "created": 1631846732,
      "updated": 1631846737
    },
    {
      "id": "6144014c8ee92a00005fcaa5",
      "text": "",
      "userId": "566fa156776c9b11008ee92a",
      "created": 1631846732,
      "updated": 1631846732
    }
  ]
}