{
  "id": "61cdcf2df6a90f001d78e6fb",
  "title": "ヨシ!",
  "created": 1640877871,
  "updated": 1640877888,
  "lines": [
    {
      "id": "61cdcf2df6a90f001d78e6fb",
      "text": "ヨシ!",
      "userId": "5e8944948a182900174bb2e2",
      "created": 1640877871,
      "updated": 1640877871
    },
    {
      "id": "61cdcf734bb2e2000059732d",
      "text": "[https://gyazo.com/dd30cee218d255f918a693c195b9cd2a]",
      "userId": "5e8944948a182900174bb2e2",
      "created": 1640877885,
      "updated": 1640877885
    }
  ]
}