{
  "id": "60b2e496d6abdc0022d3ab5c",
  "title": "京都アニメーション",
  "created": 1622336694,
  "updated": 1622336906,
  "lines": [
    {
      "id": "60b2e496d6abdc0022d3ab5c",
      "text": "京都アニメーション",
      "userId": "6055950b87138f0022246f59",
      "created": 1622336694,
      "updated": 1622336694
    },
    {
      "id": "60b2e4e8246f59000057c8e4",
      "text": "[http://www.kyotoanimation.co.jp/ 京都アニメーションホームページ]",
      "userId": "6055950b87138f0022246f59",
      "created": 1622336744,
      "updated": 1622336744
    },
    {
      "id": "60b2e4b6246f590000dc4670",
      "text": "[https://gyazo.com/160e99b7c2efbd6a043ca27e9cdb4fe2]",
      "userId": "6055950b87138f0022246f59",
      "created": 1622336694,
      "updated": 1622336732
    },
    {
      "id": "60b2e4e7246f59000057c8e3",
      "text": "[https://idy.herokuapp.com/rss/0/http://www.kyotoanimation.co.jp/information/rss.php#.svg] [https://idy.herokuapp.com/rss/1/http://www.kyotoanimation.co.jp/information/rss.php#.svg] ",
      "userId": "6055950b87138f0022246f59",
      "created": 1622336743,
      "updated": 1622336899
    },
    {
      "id": "60b2e58a246f59000057c8e8",
      "text": "",
      "userId": "6055950b87138f0022246f59",
      "created": 1622336906,
      "updated": 1622336906
    },
    {
      "id": "60b2e56b246f59000057c8e5",
      "text": "[https://idy.herokuapp.com/rss/2/http://www.kyotoanimation.co.jp/information/rss.php#.svg] [https://idy.herokuapp.com/rss/3/http://www.kyotoanimation.co.jp/information/rss.php#.svg] ",
      "userId": "6055950b87138f0022246f59",
      "created": 1622336876,
      "updated": 1622336901
    },
    {
      "id": "60b2e577246f59000057c8e7",
      "text": "",
      "userId": "6055950b87138f0022246f59",
      "created": 1622336888,
      "updated": 1622336888
    }
  ]
}