{
  "id": "6205631de4fa7000210ff8ce",
  "title": "地味な改善",
  "created": 1644520223,
  "updated": 1644537776,
  "lines": [
    {
      "id": "6205631de4fa7000210ff8ce",
      "text": "地味な改善",
      "userId": "566fa156776c9b11008ee92a",
      "created": 1644520223,
      "updated": 1644520223
    },
    {
      "id": "6205631f8ee92a00007ed949",
      "text": " [治水]",
      "userId": "566fa156776c9b11008ee92a",
      "created": 1644520223,
      "updated": 1644520228
    },
    {
      "id": "620564d18ee92a00007ed959",
      "text": "  洪水が本当に減った [増井俊之.icon]",
      "userId": "566fa156776c9b11008ee92a",
      "created": 1644520657,
      "updated": 1644520675
    },
    {
      "id": "620564e38ee92a00007ed95a",
      "text": "  洪水なんて経験したことない人がほとんどなんじゃないですか [増井俊之.icon]",
      "userId": "566fa156776c9b11008ee92a",
      "created": 1644520675,
      "updated": 1644522884
    },
    {
      "id": "620564fa8ee92a00007ed95b",
      "text": "  昔は床下浸水とかしょっちゅうだった [増井俊之.icon]",
      "userId": "566fa156776c9b11008ee92a",
      "created": 1644520699,
      "updated": 1644520711
    },
    {
      "id": "620563218ee92a00007ed94a",
      "text": " [ガス爆発]が無くなった",
      "userId": "566fa156776c9b11008ee92a",
      "created": 1644520225,
      "updated": 1644520723
    },
    {
      "id": "620563d28ee92a00007ed952",
      "text": " 伝染病が減った (多分)",
      "userId": "566fa156776c9b11008ee92a",
      "created": 1644520402,
      "updated": 1644520731
    },
    {
      "id": "62056b128ee92a00007ed971",
      "text": " 飛行機事故が減った",
      "userId": "566fa156776c9b11008ee92a",
      "created": 1644522258,
      "updated": 1644522266
    },
    {
      "id": "6205636d8ee92a00007ed94e",
      "text": "",
      "userId": "566fa156776c9b11008ee92a",
      "created": 1644520301,
      "updated": 1644520301
    },
    {
      "id": "6205636d8ee92a00007ed94f",
      "text": " こういうのは地味な技術革新とか努力とかのおかげなのだろう [増井俊之.icon]",
      "userId": "566fa156776c9b11008ee92a",
      "created": 1644520301,
      "updated": 1644520425
    },
    {
      "id": "620563858ee92a00007ed950",
      "text": " 地味すぎて誰も感謝してないかもしれないけど",
      "userId": "566fa156776c9b11008ee92a",
      "created": 1644520325,
      "updated": 1644520337
    },
    {
      "id": "620563b08ee92a00007ed951",
      "text": " 地味な努力をたたえるのが必要かも?",
      "userId": "566fa156776c9b11008ee92a",
      "created": 1644520369,
      "updated": 1644520393
    },
    {
      "id": "620563258ee92a00007ed94b",
      "text": "",
      "userId": "566fa156776c9b11008ee92a",
      "created": 1644520230,
      "updated": 1644520230
    },
    {
      "id": "620563388ee92a00007ed94c",
      "text": " 今でも[火事]は多いが... なんとかならないのかな [増井俊之.icon]",
      "userId": "566fa156776c9b11008ee92a",
      "created": 1644520249,
      "updated": 1644537776
    },
    {
      "id": "620564ab8ee92a00007ed958",
      "text": "  民家にスプリンクラーが無いのがいけないとか?",
      "userId": "566fa156776c9b11008ee92a",
      "created": 1644520619,
      "updated": 1644520630
    },
    {
      "id": "6205640a8ee92a00007ed954",
      "text": "",
      "userId": "566fa156776c9b11008ee92a",
      "created": 1644520458,
      "updated": 1644520460
    },
    {
      "id": "6205640d8ee92a00007ed955",
      "text": "#昔に比べて良くなったこと",
      "userId": "566fa156776c9b11008ee92a",
      "created": 1644520462,
      "updated": 1644520471
    },
    {
      "id": "620563398ee92a00007ed94d",
      "text": "",
      "userId": "566fa156776c9b11008ee92a",
      "created": 1644520249,
      "updated": 1644520249
    }
  ]
}