{
  "id": "5fdae8caaeccca001e7a5d5c",
  "title": "大名",
  "created": 1608181963,
  "updated": 1608181963,
  "lines": [
    {
      "id": "5fdae8caaeccca001e7a5d5c",
      "text": "大名",
      "userId": "5fa258bdb102120024d43875",
      "created": 1608181963,
      "updated": 1608181963
    },
    {
      "id": "5fdae8cbd438750000edd959",
      "text": "1万石所持している者",
      "userId": "5fa258bdb102120024d43875",
      "created": 1608181963,
      "updated": 1608181963
    },
    {
      "id": "5fdae8cbd438750000edd95a",
      "text": "",
      "userId": "5fa258bdb102120024d43875",
      "created": 1608181963,
      "updated": 1608181963
    }
  ]
}