{
  "id": "60154850bd96e5001cc354f1",
  "title": "数学記号・用語の濫用",
  "created": 1612007506,
  "updated": 1612022504,
  "lines": [
    {
      "id": "60154850bd96e5001cc354f1",
      "text": "数学記号・用語の濫用",
      "userId": "5ef2bdebb60650001e1280f0",
      "created": 1612007506,
      "updated": 1612007506
    },
    {
      "id": "601548451280f000008e8f9a",
      "text": "[書いてけ]？",
      "userId": "5ef2bdebb60650001e1280f0",
      "created": 1612007506,
      "updated": 1612007713
    },
    {
      "id": "6015484b1280f000008e8f9d",
      "text": "",
      "userId": "5ef2bdebb60650001e1280f0",
      "created": 1612007512,
      "updated": 1612007516
    },
    {
      "id": "601548501280f000008e8f9e",
      "text": "[函数][$ f(x)]",
      "userId": "5ef2bdebb60650001e1280f0",
      "created": 1612007517,
      "updated": 1612007670
    },
    {
      "id": "6015486d1280f000008e8f9f",
      "text": "　函数は[$ f]だぞ[takker.icon]",
      "userId": "5ef2bdebb60650001e1280f0",
      "created": 1612007546,
      "updated": 1612007574
    },
    {
      "id": "601548871280f000008e8fa0",
      "text": "　[$ f(x)]は[$ f]に[$ x]を代入した値",
      "userId": "5ef2bdebb60650001e1280f0",
      "created": 1612007571,
      "updated": 1612007595
    },
    {
      "id": "6015489e1280f000008e8fa1",
      "text": "　programmerだったらこのあたりの区別に敏感だと思う",
      "userId": "5ef2bdebb60650001e1280f0",
      "created": 1612007595,
      "updated": 1612007620
    },
    {
      "id": "601548ba1280f000008e8fa2",
      "text": "",
      "userId": "5ef2bdebb60650001e1280f0",
      "created": 1612007623,
      "updated": 1612007623
    },
    {
      "id": "601582e3a336820000d59a0e",
      "text": "ベクトル",
      "userId": "5e5b870dd7f3000017a33682",
      "created": 1612022499,
      "updated": 1612022504
    },
    {
      "id": "601582e3a336820000d59a0f",
      "text": "",
      "userId": "5e5b870dd7f3000017a33682",
      "created": 1612022499,
      "updated": 1612022499
    },
    {
      "id": "6015484a1280f000008e8f9b",
      "text": "#数学記号",
      "userId": "5ef2bdebb60650001e1280f0",
      "created": 1612007511,
      "updated": 1612007678
    },
    {
      "id": "601548ed1280f000008e8fa3",
      "text": "",
      "userId": "5ef2bdebb60650001e1280f0",
      "created": 1612007674,
      "updated": 1612007674
    }
  ]
}