{
  "id": "6035aeffb97b9b001c3d94cb",
  "title": "溲瓶",
  "created": 1614130945,
  "updated": 1614131147,
  "lines": [
    {
      "id": "6035aeffb97b9b001c3d94cb",
      "text": "溲瓶",
      "userId": "60226bcd2fbabe0022758921",
      "created": 1614130945,
      "updated": 1614130949
    },
    {
      "id": "6035af8c758921000099d746",
      "text": "取っ手がついており、病棟でよく見られる容れ物の一種",
      "userId": "60226bcd2fbabe0022758921",
      "created": 1614131085,
      "updated": 1614131113
    },
    {
      "id": "6035afc5758921000099d748",
      "text": "どこにでも置いておけて便利",
      "userId": "60226bcd2fbabe0022758921",
      "created": 1614131141,
      "updated": 1614131147
    },
    {
      "id": "6035af0c758921000099d742",
      "text": "よみはシュビンだが、シビンが一般的",
      "userId": "60226bcd2fbabe0022758921",
      "created": 1614130956,
      "updated": 1614130977
    },
    {
      "id": "6035af2d758921000099d743",
      "text": "",
      "userId": "60226bcd2fbabe0022758921",
      "created": 1614130989,
      "updated": 1614130989
    },
    {
      "id": "6035af2d758921000099d744",
      "text": "[みうらじゅん]も[山田風太郎]も、老化の話とともに言及している",
      "userId": "60226bcd2fbabe0022758921",
      "created": 1614130989,
      "updated": 1614131057
    },
    {
      "id": "6035af07758921000099d741",
      "text": "[落語]の演目としても有名",
      "userId": "60226bcd2fbabe0022758921",
      "created": 1614130952,
      "updated": 1614131084
    },
    {
      "id": "6035af82758921000099d745",
      "text": "",
      "userId": "60226bcd2fbabe0022758921",
      "created": 1614131075,
      "updated": 1614131075
    }
  ]
}