{
  "id": "60b5caa800d90b001c74b933",
  "title": "秒単位の課金",
  "created": 1622526634,
  "updated": 1633786237,
  "lines": [
    {
      "id": "60b5caa800d90b001c74b933",
      "text": "秒単位の課金",
      "userId": "6055950b87138f0022246f59",
      "created": 1622526634,
      "updated": 1622526642
    },
    {
      "id": "60b5cab4246f590000bb8e2f",
      "text": "[AWS]など",
      "userId": "612309a719e67d001dd0ca1c",
      "created": 1622526642,
      "updated": 1633786237
    },
    {
      "id": "61619976d0ca1c00002c811e",
      "text": "",
      "userId": "612309a719e67d001dd0ca1c",
      "created": 1633786232,
      "updated": 1633786232
    }
  ]
}