{
  "id": "60b9abd7c00e88001ce9fd17",
  "title": "麗しのサブリナ",
  "created": 1622781339,
  "updated": 1622781347,
  "lines": [
    {
      "id": "60b9abd7c00e88001ce9fd17",
      "text": "麗しのサブリナ",
      "userId": "6055950b87138f0022246f59",
      "created": 1622781339,
      "updated": 1622781339
    },
    {
      "id": "60b9ad9f246f590000eab5ef",
      "text": "https://video.unext.jp/title/SID0026260",
      "userId": "6055950b87138f0022246f59",
      "created": 1622781344,
      "updated": 1622781344
    },
    {
      "id": "60b9ad9b246f590000eab5ec",
      "text": "",
      "userId": "6055950b87138f0022246f59",
      "created": 1622781339,
      "updated": 1622781339
    },
    {
      "id": "60b9ad9b246f590000eab5ed",
      "text": "[https://gyazo.com/bf0952c8ebe9d384d613e0fcee1d154b]",
      "userId": "6055950b87138f0022246f59",
      "created": 1622781339,
      "updated": 1622781342
    },
    {
      "id": "60b9ad9d246f590000eab5ee",
      "text": "[昭和29年 1954]",
      "userId": "6055950b87138f0022246f59",
      "created": 1622781342,
      "updated": 1622781347
    },
    {
      "id": "60b9ada2246f590000eab5f1",
      "text": "[映画]",
      "userId": "6055950b87138f0022246f59",
      "created": 1622781347,
      "updated": 1622781347
    },
    {
      "id": "60b9ada1246f590000eab5f0",
      "text": "",
      "userId": "6055950b87138f0022246f59",
      "created": 1622781345,
      "updated": 1622781345
    }
  ]
}